{ "openapi": "3.0.1", "info": { "title": "Presentium API v1", "description": "The Presentium API documentation", "version": "1.0" }, "servers": [{ "url": "http://localhost:13000/v1", "description": "Generated server url" }], "security": [{ "bearerAuth": [] }], "tags": [{ "name": "Authentication", "description": "Authentication-related operations" }], "paths": { "/auth/@me": { "get": { "tags": ["Authentication"], "summary": "Get the authenticated user metadata", "operationId": "getAuthenticatedUser", "responses": { "200": { "description": "OK", "content": { "application/json": { "schema": { "$ref": "#/components/schemas/UserViewModel" } } } } } } } }, "components": { "schemas": { "UserViewModel": { "type": "object", "properties": { "username": { "type": "string" }, "email": { "type": "string" }, "displayName": { "type": "string" } } } }, "securitySchemes": { "bearerAuth": { "type": "http", "in": "header", "scheme": "bearer", "bearerFormat": "JWT" } } } }
